aiofreqlimit/__init__.py
aiofreqlimit/py.typed
aiofreqlimit-0.1.1.dist-info/WHEEL
aiofreqlimit-0.1.1.dist-info/METADATA
aiofreqlimit-0.1.1.dist-info/RECORD
