Metadata-Version: 2.3
Name: aiofreqlimit
Version: 0.1.1
Summary: Frequency limit for asyncio
Author: Gleb Chipiga
License: MIT License
Classifier: Intended Audience :: Developers
Classifier: Programming Language :: Python
Classifier: Programming Language :: Python :: 3
Classifier: Programming Language :: Python :: 3.11
Classifier: Programming Language :: Python :: 3.12
Classifier: Programming Language :: Python :: 3.13
Classifier: Programming Language :: Python :: 3.14
Classifier: License :: OSI Approved :: MIT License
Classifier: Development Status :: 4 - Beta
Classifier: Operating System :: POSIX
Classifier: Operating System :: MacOS :: MacOS X
Classifier: Operating System :: Microsoft :: Windows
Classifier: Topic :: Internet
Classifier: Framework :: AsyncIO
Requires-Python: >=3.11, <3.15
Project-URL: Homepage, https://github.com/gleb-chipiga/aiofreqlimit
